LiteEFG-0.0.5.dist-info/WHEEL
LiteEFG-0.0.5.dist-info/RECORD
LiteEFG-0.0.5.dist-info/LICENSE
LiteEFG-0.0.5.dist-info/METADATA
LiteEFG-0.0.5.dist-info/top_level.txt
LiteEFG/__init__.py
LiteEFG/_LiteEFG.cpython-312-x86_64-linux-gnu.so
LiteEFG/src/__init__.py
LiteEFG/src/Environment/__init__.py
LiteEFG/src/Environment/OpenSpiel/__init__.py
LiteEFG/src/Environment/OpenSpiel/OpenSpielToGameFile.py
LiteEFG/baselines/QFR.py
LiteEFG/baselines/MMD.py
LiteEFG/baselines/OS_MCCFR.py
LiteEFG/baselines/DOMD.py
LiteEFG/baselines/utils.py
LiteEFG/baselines/__init__.py
LiteEFG/baselines/CFR.py
LiteEFG/baselines/DCFR.py
LiteEFG/baselines/CFRplus.py
LiteEFG/GameInstances/__init__.py
